ipywui/__init__.py
ipywui/comps.py
ipywui/core.py
ipywui/components/Accordion.vue
ipywui/components/AccordionItem.vue
ipywui/components/AppLayout.vue
ipywui/components/Box.vue
ipywui/components/Button.vue
ipywui/components/Checkbox.vue
ipywui/components/Clipboard.vue
ipywui/components/Col.vue
ipywui/components/ColorPicker.vue
ipywui/components/Combobox.vue
ipywui/components/Controller.vue
ipywui/components/DatePicker.vue
ipywui/components/DateTimePicker.vue
ipywui/components/Dialog.vue
ipywui/components/Display.vue
ipywui/components/Dropdown.vue
ipywui/components/FileUpload.vue
ipywui/components/HBox.vue
ipywui/components/HtmlMath.vue
ipywui/components/Image.vue
ipywui/components/Input.vue
ipywui/components/InputNumber.vue
ipywui/components/Label.vue
ipywui/components/MarkdownViewer.vue
ipywui/components/Play.vue
ipywui/components/Progress.vue
ipywui/components/RadioButtons.vue
ipywui/components/Row.vue
ipywui/components/Select.vue
ipywui/components/SelectColors.vue
ipywui/components/SelectNumbers.vue
ipywui/components/SelectTags.vue
ipywui/components/Slider.vue
ipywui/components/Stack.vue
ipywui/components/StackItem.vue
ipywui/components/TabPane.vue
ipywui/components/Tabs.vue
ipywui/components/TimePicker.vue
ipywui/components/ToggleButton.vue
ipywui/components/ToggleButtons.vue
ipywui/components/VBox.vue
ipywui/components/Valid.vue
ipywui/components/_Stub.vue
ipywui/widgets/__init__.py
ipywui/widgets/assets/css/md_code_highlight.css
ipywui/widgets/custom/clipboard/__init__.py
ipywui/widgets/custom/clipboard/index.css
ipywui/widgets/custom/clipboard/index.js
ipywui/widgets/custom/dialog/__init__.py
ipywui/widgets/custom/dialog/index.css
ipywui/widgets/custom/dialog/index.js
ipywui/widgets/custom/message/__init__.py
ipywui/widgets/custom/message/index.css
ipywui/widgets/custom/message/index.js
panel_vuepy/__init__.py
panel_vuepy/chat.py
panel_vuepy/core.py
panel_vuepy/global.py
panel_vuepy/indicators.py
panel_vuepy/layouts.py
panel_vuepy/panes.py
vuepy_core-0.1.11.dist-info/licenses/LICENSE
vuepy_core-0.1.11.dist-info/METADATA
vuepy_core-0.1.11.dist-info/WHEEL
vuepy_core-0.1.11.dist-info/entry_points.txt
vuepy_core-0.1.11.dist-info/top_level.txt
vuepy_core-0.1.11.dist-info/RECORD
