Metadata-Version: 2.4
Name: vuepy-core
Version: 0.1.11
Summary: Vue.py is a progressive, incrementally-adoptable Python framework for building web interface in Jupyter Notebook.
Home-page: https://www.vuepy.org
Author: vuepy.org
Author-email: leilux.dev@gmail.com
License: MIT
Keywords: vue,Web UI,MVVM
Classifier: License :: OSI Approved :: MIT License
Classifier: Programming Language :: Python :: 3.7
Requires-Python: >=3.7
License-File: LICENSE
Requires-Dist: ipywidgets
Requires-Dist: markdown
Requires-Dist: anywidget
Provides-Extra: vleaflet
Requires-Dist: ipyleaflet; extra == "vleaflet"
Provides-Extra: panel
Requires-Dist: panel; extra == "panel"
Requires-Dist: jupyter_bokeh; extra == "panel"
Requires-Dist: ipywidgets_bokeh; extra == "panel"
Dynamic: author
Dynamic: author-email
Dynamic: classifier
Dynamic: description
Dynamic: description-content-type
Dynamic: home-page
Dynamic: keywords
Dynamic: license
Dynamic: license-file
Dynamic: provides-extra
Dynamic: requires-dist
Dynamic: requires-python
Dynamic: summary
